xmler.py
xmler-0.2.0.dist-info/DESCRIPTION.rst
xmler-0.2.0.dist-info/METADATA
xmler-0.2.0.dist-info/RECORD
xmler-0.2.0.dist-info/WHEEL
xmler-0.2.0.dist-info/metadata.json
xmler-0.2.0.dist-info/top_level.txt
